fake_rpi/Adafruit.py
fake_rpi/Base.py
fake_rpi/RPi.py
fake_rpi/__init__.py
fake_rpi/nxp_imu.py
fake_rpi/picamera.py
fake_rpi/serial.py
fake_rpi/smbus/__init__.py
fake_rpi/smbus/smbus.py
fake_rpi/wrappers.py
fake_rpi-0.6.3.dist-info/WHEEL
fake_rpi-0.6.3.dist-info/METADATA
fake_rpi-0.6.3.dist-info/RECORD
