Metadata-Version: 2.1
Name: fake-rpi
Version: 0.6.3
Summary: A bunch of fake interfaces for development when not using the RPi or unit testing
Home-page: https://pypi.org/project/fake_rpi/
License: MIT
Keywords: raspberry,pi,fake,fake_rpi,i2c,spi,gpio,serial
Author: walchko
Author-email: walchko@users.noreply.github.com
Requires-Python: >=3.6
Classifier: Development Status :: 4 - Beta
Classifier: Intended Audience :: Developers
Classifier: License :: OSI Approved :: MIT License
Classifier: Operating System :: OS Independent
Classifier: Programming Language :: Python :: 3
Classifier: Programming Language :: Python :: 3.6
Classifier: Programming Language :: Python :: 3.7
Classifier: Programming Language :: Python :: 3.8
Classifier: Topic :: Software Development :: Libraries
Classifier: Topic :: Software Development :: Libraries :: Application Frameworks
Classifier: Topic :: Software Development :: Libraries :: Python Modules
Requires-Dist: numpy
Project-URL: Repository, https://github.com/MomsFriendlyRobotCompany/fake_rpi
